ALU/sum1b.v
module sum1b(
        input A, 
        input B, 
        input Ci,
        output Cout,
        output Sum
    );
  
    reg [1:0] result = 'b0;
  
    assign Sum = result[0];
    assign Cout = result[1];
  
    always@(*) begin
      result = A+B+Ci;
    end
    
  endmodule

RESTADOR/sum4b.v
`include "sum1b.v"

module sum4b (
        input  [3:0] A,
        input  [3:0] B,
        input Ci,
        output Cout,
        output [3:0] Sum
    );

  wire c1,c2,c3;
  wire c_out; 


  sum1b s0 (.A(A[0]), .B(B[0]), .Ci(Ci),  .Cout(c1) ,.Sum(Sum[0]));
  sum1b s1 (.A(A[1]), .B(B[1]), .Ci(c1), .Cout(c2) ,.Sum(Sum[1]));
  sum1b s2 (.A(A[2]), .B(B[2]), .Ci(c2), .Cout(c3) ,.Sum(Sum[2]));
  sum1b s3 (.A(A[3]), .B(B[3]), .Ci(c3), .Cout(Cout) ,.Sum(Sum[3]));

endmodule

RESTADOR/rest4b.v
`include "sum4b.v"

module rest4b (
    input [3:0] A,
    input [3:0] B,
    input sel,
    output Cout,
    output [3:0] Rest
    );

  wire c1;
  wire b0,b1,b2,b3;
  wire c_out; 


  assign b0 = B[0]^sel;
  assign b1 = B[1]^sel;
  assign b2 = B[2]^sel;
  assign b3 = B[3]^sel;
  

  sum4b s0 (.A(A), .B({b3,b2,b1,b0}), .Ci(sel),  .Cout(Cout) ,.Sum(Rest));
  
  case (status)
    NEG:  
    default: 
  endcase
endmodule

RESTADOR/rest4b_tb.v
`include "rest4b.v"
`timescale 1ns/1ns

module rest4b_tb();

    reg [3:0] xi_tb;
    reg [3:0] yi_tb;
    reg sel_tb;
    wire co_tb;
    wire [3:0] zi_tb;
  
    // Instantiate the Unit Under Test (UUT)
    rest4b uut (
      .sel(sel_tb),
      .A(xi_tb), 
      .B(yi_tb), 
      .Cout(co_tb), 
      .Rest(zi_tb)
    );
  
  initial begin
    sel_tb=1;
    xi_tb=0;
    for (yi_tb = 0; yi_tb < 15; yi_tb = yi_tb + 1) begin
      if (yi_tb==0) begin
        xi_tb=xi_tb+1;
      end
      #5 $display("el valor de %d - %d = %d", xi_tb,yi_tb,zi_tb);
    end
    $finish;
  end      

  initial begin: TEST_CASE
		$dumpfile("rest4b_tb.vcd");
		$dumpvars(-1, uut);
	end
  
  endmodule

RESTADOR/build/rest4b_tb.vcd
$date
	Wed Sep 11 21:53:31 2024
$end
$version
	Icarus Verilog
$end
$timescale
	1ns
$end
$scope module rest4b_tb $end
$scope module uut $end
$var wire 4 ! A [3:0] $end
$var wire 4 " B [3:0] $end
$var wire 1 # b0 $end
$var wire 1 $ b1 $end
$var wire 1 % b2 $end
$var wire 1 & b3 $end
$var wire 1 ' sel $end
$var wire 4 ( Rest [3:0] $end
$var wire 1 ) Cout $end
$scope module s0 $end
$var wire 4 * A [3:0] $end
$var wire 4 + B [3:0] $end
$var wire 1 ' Ci $end
$var wire 1 , c3 $end
$var wire 1 - c2 $end
$var wire 1 . c1 $end
$var wire 4 / Sum [3:0] $end
$var wire 1 ) Cout $end
$scope module s0 $end
$var wire 1 0 A $end
$var wire 1 1 B $end
$var wire 1 ' Ci $end
$var wire 1 2 Sum $end
$var wire 1 . Cout $end
$var reg 2 3 result [1:0] $end
$upscope $end
$scope module s1 $end
$var wire 1 4 A $end
$var wire 1 5 B $end
$var wire 1 . Ci $end
$var wire 1 6 Sum $end
$var wire 1 - Cout $end
$var reg 2 7 result [1:0] $end
$upscope $end
$scope module s2 $end
$var wire 1 8 A $end
$var wire 1 9 B $end
$var wire 1 - Ci $end
$var wire 1 : Sum $end
$var wire 1 , Cout $end
$var reg 2 ; result [1:0] $end
$upscope $end
$scope module s3 $end
$var wire 1 < A $end
$var wire 1 = B $end
$var wire 1 , Ci $end
$var wire 1 > Sum $end
$var wire 1 ) Cout $end
$var reg 2 ? result [1:0] $end
$upscope $end
$upscope $end
$upscope $end
$upscope $end
$enddefinitions $end
$comment Show the parameter values. $end
$dumpall
$end
#0
$dumpvars
b10 ?
0>
1=
0<
b10 ;
0:
19
08
b10 7
06
15
04
b11 3
12
11
10
b1 /
1.
1-
1,
b1111 +
b1 *
1)
b1 (
1'
1&
1%
1$
1#
b0 "
b1 !
$end
#5
b0 (
b0 /
02
b10 3
01
b1110 +
0#
b1 "
#10
1>
0)
b1 ?
1:
0,
b1 ;
12
b1111 (
b1111 /
16
0-
b11 3
b1 7
11
05
1#
b1101 +
0$
b10 "
#15
b1110 (
b1110 /
02
b10 3
01
b1100 +
0#
b11 "
#20
12
06
1-
b1101 (
b1101 /
1:
b11 3
b10 7
b1 ;
11
15
09
1#
1$
b1011 +
0%
b100 "
#25
b1100 (
b1100 /
02
b10 3
01
b1010 +
0#
b101 "
#30
0:
b0 ;
12
b1011 (
b1011 /
16
0-
b11 3
b1 7
11
05
1#
b1001 +
0$
b110 "
#35
b1010 (
b1010 /
02
b10 3
01
b1000 +
0#
b111 "
#40
1,
12
06
1-
0:
b1001 (
b1001 /
1>
b11 3
b10 7
b10 ;
b1 ?
11
15
19
0=
1#
1$
1%
b111 +
0&
b1000 "
#45
b1000 (
b1000 /
02
b10 3
01
b110 +
0#
b1001 "
#50
0>
b0 ?
1:
0,
b1 ;
12
b111 (
b111 /
16
0-
b11 3
b1 7
11
05
1#
b101 +
0$
b1010 "
#55
b110 (
b110 /
02
b10 3
01
b100 +
0#
b1011 "
#60
12
06
1-
b101 (
b101 /
1:
b11 3
b10 7
b1 ;
11
15
09
1#
1$
b11 +
0%
b1100 "
#65
b100 (
b100 /
02
b10 3
01
b10 +
0#
b1101 "
#70
0:
b0 ;
12
b11 (
b11 /
16
0-
b11 3
b1 7
11
05
1#
b1 +
0$
b1110 "
#75
b10 (
b10 /
02
b10 3
01
b0 +
0#
b1111 "
